pepmeasure/__init__.py
pepmeasure/__main__.py
pepmeasure/api.py
pepmeasure/constants.py
pepmeasure/features.py
pepmeasure/maxquant.py
pepmeasure/plots.py
pepmeasure/utils.py
pepmeasure-0.4.0.dist-info/licenses/LICENSE
pepmeasure-0.4.0.dist-info/METADATA
pepmeasure-0.4.0.dist-info/WHEEL
pepmeasure-0.4.0.dist-info/entry_points.txt
pepmeasure-0.4.0.dist-info/top_level.txt
pepmeasure-0.4.0.dist-info/RECORD
